todoist_auto/__init__.py
todoist_auto/gov_tod_label.py
todoist_auto/models.py
todoist_auto/refresh_day_routine.py
todoist_auto/rm_all_secs.py
todoist_auto/rm_empty_sections.py
todoist_auto/sort_plnd_tod.py
todoist_auto/util.py
todoist_auto-11.5.2.dist-info/METADATA
todoist_auto-11.5.2.dist-info/WHEEL
todoist_auto-11.5.2.dist-info/RECORD
